setup.cfg
setup.py
coralogix/__init__.py
coralogix/coralogix_https_agent.py
coralogix/coralogix_https_logging.py
coralogix/coralogix_logging.py
coralogix/http.py
coralogix/log_aggregator.py
coralogix/logger.py
coralogix/serialization.py
coralogix.egg-info/PKG-INFO
coralogix.egg-info/SOURCES.txt
coralogix.egg-info/dependency_links.txt
coralogix.egg-info/requires.txt
coralogix.egg-info/top_level.txt
coralogix/config/__init__.py
coralogix/config/constraints.py
coralogix/config/settings.py