Metadata-Version: 1.1
Name: coralogix
Version: 0.2.6.0
Summary: Coralogix Python SDK
Home-page: http://www.coralogix.com/
Author: Coralogix Ltd.
Author-email: info@coralogix.com
License: Apache Software License v2.0
Platform: UNKNOWN
Classifier: Programming Language :: Python
Classifier: Development Status :: 5 - Production/Stable
Classifier: Topic :: Utilities
Classifier: Intended Audience :: Developers
Classifier: License :: OSI Approved :: Apache Software License
